{
  "name": "Offensive Recovery",
  "category": "Equipment",
  "rarity": "Equipment",
  "reqs": "()",
  "additional_info": "If all of your equipped Mantras have a Might Gem equipped, hitting your opponent's block with Mantras will restore your posture.",
  "count_towards_talent_total": false,
  "icon": "Fist",
  "roll2able": false,
  "vaulted": false,
  "voi": false,
  "desc": "If all your mantras have Might Gems equipped, lose posture any time you hit opponents block with a mantra.",
  "voi_only": false
}