{
  "name": "Flame Demon Horns",
  "equippable": true,
  "type": "Head",
  "rarity": "Legendary",
  "set": null,
  "variants": [],
  "talents": [
    "Mindspark"
  ],
  "innates": {
    "Posture": {
      "value": 1,
      "percentage": false
    },
    "Flame Resistance": {
      "value": 8,
      "percentage": true
    }
  },
  "pips": {
    "Rare": 1
  },
  "reqs": "flame_demon_horns := ()",
  "voi": true,
  "desc": "An otherworldly set of faux horns. Faint scratches on the back spell something like 'Aazel', though the writing is weathered almost beyond recognition. Whoever wore these must have long since drowned. Strangely, they're warm to the touch.",
  "voi_only": true
}
